deknp-0.1.104.dist-info/METADATA
deknp-0.1.104.dist-info/WHEEL
deknp-0.1.104.dist-info/entry_points.txt
deknp/__init__.py
deknp/click/__entry__.py
deknp/click/__init__.py
deknp/click/env.py
deknp/core/__init__.py
deknp/core/base/__init__.py
deknp/core/base/env_vars.py
deknp/core/plugins/__init__.py
deknp/core/plugins/babel_config.py
deknp/core/plugins/base/__init__.py
deknp/core/plugins/dv3.py
deknp/core/plugins/dv3_env_vars.py
deknp/core/plugins/dv3_server.py
deknp/core/plugins/dv3_svg.py
deknp/core/plugins/dv3_yaml.py
deknp/core/plugins/fix/__init__.py
deknp/core/plugins/fix/svgpathtools.py
deknp/core/plugins/images.py
deknp/core/plugins/npmrc.py
deknp/core/plugins/override_root.py
deknp/core/plugins/package_json.py
deknp/core/plugins/packages.py
deknp/core/plugins/replace.py
deknp/core/plugins/requests.py
deknp/core/plugins/tsconfig.py
deknp/core/plugins/uniapp_vars.py
deknp/core/plugins/vite_config.py
deknp/core/plugins/vue_config.py
deknp/core/run.py
deknp/gen/__init__.py
deknp/gen/templatefiles/shell/.deknp.apprebuild.pysh
deknp/gen/templatefiles/shell/.deknp.appupdate.pysh
deknp/gen/templatefiles/shell/.deknp.asapp.pysh
deknp/gen/templatefiles/shell/.deknp.dist.pysh
deknp/gen/templatefiles/shell/.deknp.pn.pysh
deknp/gen/tmpl.py
deknp-0.1.104.dist-info/RECORD
