Metadata-Version: 2.1
Name: deknp
Version: 0.1.104
Summary: Extending from npm
Author-Email: sanzenwin <sanzenwin@gmail.com>
License: MIT
Requires-Python: >=3.10
Requires-Dist: json5<=1.6.4
Requires-Dist: svgpathtools<=1.6.1
Requires-Dist: dektools[dyna,yaml]<1.0.0
Requires-Dist: dekgen<1.0.0
Requires-Dist: dekmedia[svg]<1.0.0
